mymcp/__init__.py
mymcp/data_types/__init__.py
mymcp/data_types/chunk.py
mymcp/data_types/entity.py
mymcp/data_types/nbt.py
mymcp/data_types/particle.py
mymcp/data_types/protocol.py
mymcp/data_types/slot.py
mymcp/packets/__init__.py
mymcp/packets/enums.py
mymcp/packets/v769.py
mymcp-0.2.0.dist-info/licenses/LICENSE
mymcp-0.2.0.dist-info/METADATA
mymcp-0.2.0.dist-info/WHEEL
mymcp-0.2.0.dist-info/top_level.txt
mymcp-0.2.0.dist-info/RECORD
