Metadata-Version: 2.4
Name: mymcp
Version: 0.2.0
Summary: Encode and Decode the DataType and Protocols (Almost 100%) of the Minecraft (Java Edition) version 1.21.4 (Protocol 769) in Python. 
Author-email: Me2sY <me2sy@outlook.com>
Project-URL: Homepage, https://github.com/me2sy/MYMCP
Project-URL: Issues, https://github.com/me2sy/MYMCP/issues
Keywords: Minecraft,Protocols,Game
Classifier: Programming Language :: Python :: 3
Classifier: Development Status :: 4 - Beta
Classifier: License :: OSI Approved :: GNU General Public License v3 (GPLv3)
Classifier: Natural Language :: Chinese (Simplified)
Classifier: Topic :: Games/Entertainment
Requires-Python: >=3.12
License-File: LICENSE
Requires-Dist: mutf8
Dynamic: license-file
